krong/__init__.py
krong/alias.py
krong/factory.py
krong/krong.py
krong/task.py
krong/tasks/__init__.py
krong/tasks/hangulizer/__init__.py
krong/tasks/josa/__init__.py
krong/tasks/romanizer/__init__.py
krong/tasks/sent_tokenizer/__init__.py
krong/tasks/summarizer/__init__.py
krong/tasks/tagger/__init__.py
krong/tasks/tagger/tasks.py
krong/tasks/tagger/usages.py
krong/tasks/tagger/dict/__init__.py
krong/tasks/tagger/dict/character_definition.py
krong/tasks/tagger/dict/connection_costs.py
krong/tasks/tagger/dict/dictionary.py
krong/tasks/tagger/dict/known_dictionary.py
krong/tasks/tagger/dict/trie.py
krong/tasks/tagger/dict/unknown_dictionary.py
krong/tasks/tagger/dict/user_dictionary.py
krong/tasks/tagger/modules/__init__.py
krong/tasks/tagger/modules/char_unicode.py
krong/tasks/tagger/modules/decompound_token.py
krong/tasks/tagger/modules/dictionary_token.py
krong/tasks/tagger/modules/korean_analyzer.py
krong/tasks/tagger/modules/korean_posstop_filter.py
krong/tasks/tagger/modules/korean_tokenizer.py
krong/tasks/tagger/modules/pos.py
krong/tasks/tagger/modules/post_processing.py
krong/tasks/tagger/modules/synonym_graph_filter.py
krong/tasks/tagger/modules/token.py
krong/tasks/tagger/modules/token_attribute.py
tests/__init__.py
tests/test_tagger.py
krong-0.0.0.dist-info/LICENSE
krong-0.0.0.dist-info/METADATA
krong-0.0.0.dist-info/WHEEL
krong-0.0.0.dist-info/top_level.txt
krong-0.0.0.dist-info/RECORD
