Metadata-Version: 2.1
Name: krong
Version: 0.0.0
Summary: KRONG: KoRean language processing toolkit based On Non-neural methods for General purpose
Home-page: https://github.com/hyunwoongko/krong
Author: Hyunwoong Ko
Author-email: kevin.ko@tunib.ai
License: UNKNOWN
Platform: UNKNOWN
Classifier: Intended Audience :: Developers
Classifier: Intended Audience :: Science/Research
Classifier: Development Status :: 3 - Alpha
Classifier: License :: OSI Approved :: Apache Software License
Classifier: Programming Language :: Python :: 3
Classifier: Programming Language :: Python :: 3.6
Classifier: Programming Language :: Python :: 3.7
Classifier: Programming Language :: Python :: 3.8
Classifier: Programming Language :: Python :: 3.9
Classifier: Topic :: Software Development :: Libraries
Requires-Python: >=3.6.0
